<?xml version="1.0" encoding="UTF-8"?>
<database defaultPhpNamingMethod="underscore" heavyIndexing="false" name="propel" defaultIdMethod="native" noxsd="true" package="lib.model.air"><table skipSql="false" abstract="false" name="tb_inomaestra_air" phpName="InoMaestraAir"><column primaryKey="false" autoIncrement="false" lazyLoad="false" name="ca_fchreferencia" type="date" required="true"/><column autoIncrement="false" lazyLoad="false" name="ca_referencia" type="varchar" required="true" primaryKey="true"/><column primaryKey="false" required="false" autoIncrement="false" lazyLoad="false" name="ca_impoexpo" type="varchar"/><column primaryKey="false" required="false" autoIncrement="false" lazyLoad="false" name="ca_origen" type="varchar"/><column primaryKey="false" required="false" autoIncrement="false" lazyLoad="false" name="ca_destino" type="varchar"/><column primaryKey="false" required="false" autoIncrement="false" lazyLoad="false" name="ca_modalidad" type="varchar"/><column primaryKey="false" required="false" autoIncrement="false" lazyLoad="false" name="ca_idlinea" type="integer"/><column primaryKey="false" required="false" autoIncrement="false" lazyLoad="false" name="ca_mawb" type="varchar"/><column primaryKey="false" required="false" autoIncrement="false" lazyLoad="false" name="ca_piezas" type="integer"/><column primaryKey="false" required="false" autoIncrement="false" lazyLoad="false" name="ca_peso" type="numeric"/><column primaryKey="false" required="false" autoIncrement="false" lazyLoad="false" name="ca_pesovolumen" type="numeric"/><column primaryKey="false" required="false" autoIncrement="false" lazyLoad="false" name="ca_observaciones" type="varchar"/><column primaryKey="false" required="false" autoIncrement="false" lazyLoad="false" name="ca_fchcreado" type="date"/><column primaryKey="false" required="false" autoIncrement="false" lazyLoad="false" name="ca_usucreado" type="varchar"/><column primaryKey="false" required="false" autoIncrement="false" lazyLoad="false" name="ca_fchactualizado" type="date"/><column primaryKey="false" required="false" autoIncrement="false" lazyLoad="false" name="ca_usuactualizado" type="varchar"/><column primaryKey="false" required="false" autoIncrement="false" lazyLoad="false" name="ca_fchliquidado" type="date"/><column primaryKey="false" required="false" autoIncrement="false" lazyLoad="false" name="ca_usuliquidado" type="varchar"/><column primaryKey="false" required="false" autoIncrement="false" lazyLoad="false" name="ca_fchcerrado" type="date"/><column primaryKey="false" required="false" autoIncrement="false" lazyLoad="false" name="ca_usucerrado" type="varchar"/><foreign-key onDelete="none" onUpdate="none" foreignTable="tb_transporlineas"><reference local="ca_idlinea" foreign="ca_idlinea"/></foreign-key></table><table skipSql="false" abstract="false" name="tb_inoclientes_air" phpName="InoClientesAir"><column autoIncrement="false" lazyLoad="false" name="ca_referencia" type="varchar" required="true" primaryKey="true"/><column autoIncrement="false" lazyLoad="false" name="ca_idcliente" type="integer" required="true" primaryKey="true"/><column autoIncrement="false" lazyLoad="false" name="ca_hawb" type="varchar" required="true" primaryKey="true"/><column primaryKey="false" required="false" autoIncrement="false" lazyLoad="false" name="ca_idreporte" type="varchar"/><column primaryKey="false" required="false" autoIncrement="false" lazyLoad="false" name="ca_idproveedor" type="integer"/><column primaryKey="false" required="false" autoIncrement="false" lazyLoad="false" name="ca_proveedor" type="varchar"/><column primaryKey="false" required="false" autoIncrement="false" lazyLoad="false" name="ca_numpiezas" type="integer"/><column primaryKey="false" required="false" autoIncrement="false" lazyLoad="false" name="ca_peso" type="integer"/><column primaryKey="false" required="false" autoIncrement="false" lazyLoad="false" name="ca_volumen" type="integer"/><column primaryKey="false" required="false" autoIncrement="false" lazyLoad="false" name="ca_numorden" type="varchar"/><column primaryKey="false" required="false" autoIncrement="false" lazyLoad="false" name="ca_loginvendedor" type="varchar"/><column primaryKey="false" required="false" autoIncrement="false" lazyLoad="false" name="ca_fchcreado" type="timestamp"/><column primaryKey="false" required="false" autoIncrement="false" lazyLoad="false" name="ca_usucreado" type="varchar"/><column primaryKey="false" required="false" autoIncrement="false" lazyLoad="false" name="ca_fchactualizado" type="timestamp"/><column primaryKey="false" required="false" autoIncrement="false" lazyLoad="false" name="ca_usuactualizado" type="varchar"/><column primaryKey="false" required="false" autoIncrement="false" lazyLoad="false" name="ca_idbodega" type="integer"/><foreign-key onDelete="none" onUpdate="none" foreignTable="tb_reportes"><reference local="ca_idreporte" foreign="ca_idreporte"/></foreign-key><foreign-key onDelete="none" onUpdate="none" foreignTable="tb_terceros"><reference local="ca_idproveedor" foreign="ca_idtercero"/></foreign-key><foreign-key onDelete="none" onUpdate="none" foreignTable="tb_inomaestra_air"><reference local="ca_referencia" foreign="ca_referencia"/></foreign-key></table><table skipSql="false" abstract="false" name="tb_inoingresos_air" phpName="InoIngresosAir"><column autoIncrement="false" lazyLoad="false" name="ca_referencia" type="varchar" required="true" primaryKey="true"/><column autoIncrement="false" lazyLoad="false" name="ca_idcliente" type="integer" required="true" primaryKey="true"/><column autoIncrement="false" lazyLoad="false" name="ca_hawb" type="varchar" required="true" primaryKey="true"/><column autoIncrement="false" lazyLoad="false" name="ca_factura" type="varchar" required="true" primaryKey="true"/><column primaryKey="false" required="false" autoIncrement="false" lazyLoad="false" name="ca_fchfactura" type="date"/><column primaryKey="false" required="false" autoIncrement="false" lazyLoad="false" name="ca_valor" type="numeric"/><column primaryKey="false" required="false" autoIncrement="false" lazyLoad="false" name="ca_reccaja" type="varchar"/><column primaryKey="false" required="false" autoIncrement="false" lazyLoad="false" name="ca_fchpago" type="date"/><column primaryKey="false" required="false" autoIncrement="false" lazyLoad="false" name="ca_tcalaico" type="numeric"/><column primaryKey="false" required="false" autoIncrement="false" lazyLoad="false" name="ca_fchcreado" type="timestamp"/><column primaryKey="false" required="false" autoIncrement="false" lazyLoad="false" name="ca_usucreado" type="varchar"/><foreign-key onDelete="none" onUpdate="none" foreignTable="tb_inomaestra_air"><reference local="ca_referencia" foreign="ca_referencia"/></foreign-key><foreign-key onDelete="none" onUpdate="none" foreignTable="tb_clientes"><reference local="ca_idcliente" foreign="ca_idcliente"/></foreign-key></table></database>
